CHANGELOG.md
LICENSE.txt
MANIFEST.in
README.md
setup.cfg
setup.py
castletheme/__init__.py
castletheme.sparkling.egg-info/PKG-INFO
castletheme.sparkling.egg-info/SOURCES.txt
castletheme.sparkling.egg-info/dependency_links.txt
castletheme.sparkling.egg-info/entry_points.txt
castletheme.sparkling.egg-info/namespace_packages.txt
castletheme.sparkling.egg-info/not-zip-safe
castletheme.sparkling.egg-info/requires.txt
castletheme.sparkling.egg-info/top_level.txt
castletheme/sparkling/__init__.py
castletheme/sparkling/configure.zcml
castletheme/sparkling/profiles/default/registry.xml
castletheme/sparkling/profiles/default/theme.xml
castletheme/sparkling/theme_resources/index.html
castletheme/sparkling/theme_resources/integration.css
castletheme/sparkling/theme_resources/integration.css.map
castletheme/sparkling/theme_resources/integration.less
castletheme/sparkling/theme_resources/manifest.cfg
castletheme/sparkling/theme_resources/plain.html
castletheme/sparkling/theme_resources/style.css
castletheme/sparkling/theme_resources/fragments/follow-us.pt
castletheme/sparkling/theme_resources/fragments/popular-tags.pt
castletheme/sparkling/theme_resources/fragments/sitetitle.pt
castletheme/sparkling/theme_resources/fragments/tag-cloud.pt
castletheme/sparkling/theme_resources/inc/custom-header.php
castletheme/sparkling/theme_resources/inc/customizer.php
castletheme/sparkling/theme_resources/inc/extras.php
castletheme/sparkling/theme_resources/inc/jetpack.php
castletheme/sparkling/theme_resources/inc/metaboxes.php
castletheme/sparkling/theme_resources/inc/navwalker.php
castletheme/sparkling/theme_resources/inc/template-tags.php
castletheme/sparkling/theme_resources/inc/wpcom.php
castletheme/sparkling/theme_resources/inc/css/bootstrap.css
castletheme/sparkling/theme_resources/inc/css/bootstrap.min.css
castletheme/sparkling/theme_resources/inc/css/flexslider.css
castletheme/sparkling/theme_resources/inc/css/font-awesome.min.css
castletheme/sparkling/theme_resources/inc/fonts/FontAwesome.otf
castletheme/sparkling/theme_resources/inc/fonts/fontawesome-webfont.eot
castletheme/sparkling/theme_resources/inc/fonts/fontawesome-webfont.svg
castletheme/sparkling/theme_resources/inc/fonts/fontawesome-webfont.ttf
castletheme/sparkling/theme_resources/inc/fonts/fontawesome-webfont.woff
castletheme/sparkling/theme_resources/inc/fonts/fontawesome-webfont.woff2
