Metadata-Version: 2.1
Name: castletheme.sparkling
Version: 1.0.4
Summary: Implementation of the WordPress Sparkling theme for CastleCMS
Home-page: https://www.wildcardcorp.com
Author: Wildcard Corp.
Author-email: corporate@wildcardcorp.com
License: GPLv3+
Keywords: castlecms plone theme
Platform: UNKNOWN
Classifier: Framework :: Plone
Classifier: Framework :: Plone :: 5.0
Classifier: Programming Language :: Python
Classifier: Programming Language :: Python :: 2.7
Classifier: Topic :: Software Development :: Libraries :: Python Modules
Classifier: License :: OSI Approved :: GNU General Public License v3 or later (GPLv3+)
